paytrek/__init__.py
paytrek/client.py
paytrek-0.0.7.dist-info/DESCRIPTION.rst
paytrek-0.0.7.dist-info/METADATA
paytrek-0.0.7.dist-info/RECORD
paytrek-0.0.7.dist-info/WHEEL
paytrek-0.0.7.dist-info/metadata.json
paytrek-0.0.7.dist-info/top_level.txt
