Metadata-Version: 2.0
Name: paytrek
Version: 0.0.7
Summary: Python client library for Paytrek API
Home-page: https://bitbucket.org/erkanay/paytrek-python-client
Author: Erkan Ay
Author-email: erkanaycom@gmail.com
License: MIT
Keywords: paytrek,client,payment,gateway
Platform: UNKNOWN
Classifier: Intended Audience :: Developers
Classifier: License :: OSI Approved :: MIT License
Classifier: Programming Language :: Python :: 2.7
Classifier: Programming Language :: Python :: 3
Requires-Dist: requests
